LICENSE
README.md
djangOK
setup.py
djangOK/__init__.py
djangOK/djangOK
djangOK/djangOK.py
djangOK.egg-info/PKG-INFO
djangOK.egg-info/SOURCES.txt
djangOK.egg-info/dependency_links.txt
djangOK.egg-info/requires.txt
djangOK.egg-info/top_level.txt